{
    "cli": true,
    "target": "directory",
    "adapterName": "alpha-ess",
    "title": "Alpha ESS",
    "description": "Read and write data from and to Alpha ESS systems.",
    "keywords": ["photovoltaik"],
    "expert": "no",
    "features": ["adapter"],
    "adminFeatures": [],
    "type": "energy",
    "startMode": "daemon",
    "connectionType": "cloud",
    "dataSource": "poll",
    "connectionIndicator": "no",
    "language": "JavaScript",
    "nodeVersion": "14",
    "adminUi": "json",
    "tools": ["ESLint", "type checking", "Prettier"],
    "releaseScript": "yes",
    "devServer": "no",
    "indentation": "Space (4)",
    "quotes": "single",
    "es6class": "yes",
    "authorName": "Gaspode",
    "authorGithub": "Gaspode69",
    "authorEmail": "gaspode69@online.de",
    "gitRemoteProtocol": "HTTPS",
    "gitCommit": "no",
    "defaultBranch": "main",
    "license": "MIT License",
    "dependabot": "yes",
    "creatorVersion": "2.3.0"
}
